<odoo>

    <!-- ============ Form View of forward button============= -->
        <record id="transfer_pf_wizard_form_view" model="ir.ui.view">
            <field name="name">employee.pf.transfer.wizard.form</field>
            <field name="model">employee.pf.transfer.wizard</field>
            <field name="arch" type="xml">
                <form string="Transfer PF">
                    <group>
                        <field name="employee_pf" invisible="1"/>
                        <field name="transfer_details">
                        <tree editable="bottom">
                            <field name="date" required="1"/>
                            <field name="type" required="1"/>
                            <field name="pf_code" required="1"/>
                            <field name="description" required="1"/>
                            <field name="amount" required="1" sum="Total"/>
                            <field name="reference" required="1"/>
                        </tree>
                        </field>
                    </group>
                    <footer>
                        <button name = "confirm_button" string = "Confirm" type = "object" class="oe_highlight"/>
                        <button name="cancel" string = "Cancel" special = "cancel"/>
                    </footer>
                </form>
            </field>
        </record>

     <!-- =============== Action View of forward button================ -->
     <record id="button_transfer_pf_button_wizard_action_view" model="ir.actions.act_window">
         <field name="name">Transfer PF</field>
         <field name="type">ir.actions.act_window</field>
         <field name="res_model">employee.pf.transfer.wizard</field>
         <field name="view_type">form</field>
         <field name="view_mode">form</field>
         <field name="target">new</field>
    </record>

</odoo>