<odoo>

    <!-- ============ Form View of forward button============= -->
        <record id="forward_button_form_view" model="ir.ui.view">
            <field name="name">file.wizard.form</field>
            <field name="model">file.wizard</field>
            <field name="arch" type="xml">
                <form string="Correspondence information">
                        <group string="Send To">
                            <group>
                                <field name = "department" options="{'no_create_edit': True, 'no_create': True}" required="1"/>
                                <field name = "jobposition" options="{'no_create_edit': True, 'no_create': True}" required="1"/>
                            </group>
                            <group>
                                 <field name = "employee" options="{'no_create_edit': True, 'no_create': True}" required="1"/>
                                 <field name = "user"/>
                                 <field name="defid" invisible = "1"/>
                            </group>
                        </group>
<!--                    <group string="Secondary User 1">-->
<!--                        <group>-->
<!--                            <field name = "s1department"/>-->
<!--                            <field name = "s1jobposition"/>-->
<!--                            </group>-->
<!--                            <group>-->
<!--                                 <field name = "s1employee"/>-->
<!--                                 <field name = "s1user"/>-->
<!--                            </group>-->
<!--                    </group>-->
<!--                    <group string="Secondary User 2">-->
<!--                        <group>-->
<!--                            <field name = "s2department"/>-->
<!--                            <field name = "s2jobposition"/>-->
<!--                            </group>-->
<!--                            <group>-->
<!--                                 <field name = "s2employee"/>-->
<!--                                 <field name = "s2user"/>-->
<!--                            </group>-->
<!--                    </group>-->
<!--                    <group string="Secondary User 3">-->
<!--                        <group>-->
<!--                            <field name = "s3department"/>-->
<!--                            <field name = "s3jobposition"/>-->
<!--                            </group>-->
<!--                            <group>-->
<!--                                 <field name = "s3employee"/>-->
<!--                                 <field name = "s3user"/>-->
<!--                            </group>-->
<!--                    </group>-->
                    <separator string="Cc"/>
                    <field name="sec_own_ids">
                        <tree editable="bottom">
                            <field name="sec_own_id" invisible="1"/>
                            <field name="department" options="{'no_create_edit': True, 'no_create': True}" required="1"/>
                            <field name="jobposition" options="{'no_create_edit': True, 'no_create': True}" required="1"/>
                            <field name="employee" options="{'no_create_edit': True, 'no_create': True}" required="1"/>
                            <field name="user"/>
                        </tree>
                    </field>
                    <field name="remarks" nolabel="1" required="1" placeholder="Remarks"/>
                     <footer>
                        <button name = "confirm_button" string = "Confirm" type = "object" class="oe_highlight"/>
                        <button name="cancel" string = "Cancel" special = "cancel"/>
                    </footer>
                </form>
            </field>
        </record>

     <!-- =============== Action View of forward button================ -->
     <record id="forward_button_wizard_action_view" model="ir.actions.act_window">
         <field name="name">Forward</field>
         <field name="type">ir.actions.act_window</field>
         <field name="res_model">file.wizard</field>
         <field name="view_type">form</field>
         <field name="view_mode">form</field>
         <field name="target">new</field>
    </record>

</odoo>