<odoo>
    <!--==========Form view of Employee Indent Advance==========-->
    <record id="employeeIndent_request_form_view" model="ir.ui.view">
        <field name="name">indent.request.form</field>
        <field name="model">indent.request</field>
        <field name="arch" type="xml">
            <form string="Indent">
                <header>
                    <button name="button_to_approve" string="Send for Approval" class="oe_highlight" type="object" states="draft"/>
                     <button name="button_reset_to_draft" string="Reset to draft" type="object" states="to_approve"/>
                    <button name="button_approved" string="Approve" class="oe_highlight" type="object" states="to_approve" groups="indent_stpi.group_Indent_request_manager"/>
                    <button name="button_reject" string="Reject" type="object" states="to_approve" groups="indent_stpi.group_Indent_request_manager"/>
                    <field name="state" widget="statusbar" statusbar_visible="draft,to_approve,approved,rejected" />
                </header>
                <sheet>
                    <group>
                        <group>
                            <field name="indent_sequence" readonly="True"/>
                            <field name="employee_id" readonly="1" required="1"/>
                            <field name="branch_id" readonly="1"/>
                            <field name="requested_date" readonly="1"/>
                        </group>
                        <group>
                            <field name="job_id" readonly="1"/>
                            <field name="department_id" readonly="1"/>
                            <field name="indent_type" readonly="1"/>
                        </group>
                        <group>
                        </group>
                    </group>
                    <notebook>
                        <page string="Item Details">
                            <field name="item_ids" attrs="{'readonly': [('state', '!=', 'draft')]}">
                                <tree editable="bottom">
                                    <field name="request_id" invisible="1"/>
                                    <field name="item_category_id" required="1" options="{'no_create_edit': True}"/>
                                    <field name="item_id" required="1" options="{'no_create_edit': True}"  domain="[('child_indent_stock','=',item_category_id)]"/>
                                    <field name="specification" required="1"/>
                                    <field name="requested_quantity" required="1"/>
                                    <field name="requested_date" required="1"/>
                                    <field name="issue_approved" invisible="1"/>
                                    <field name="approved_quantity" attrs="{'invisible': [('issue_approved', '=', False)],'readonly': [('issue_approved', '!=', False)]}"/>
                                    <field name="approved_date" attrs="{'invisible': [('issue_approved', '=', False)],'readonly': [('issue_approved', '!=', False)]}"/>
                                </tree>
                            </field>
                        </page>
                    </notebook>

                </sheet>
                <div class="oe_chatter">
                        <field name="message_follower_ids" widget="mail_followers"/>
                        <field name="activity_ids" widget="mail_activity"/>
                        <field name="message_ids" widget="mail_thread"/>
                    </div>
            </form>
        </field>
    </record>
    

    <!--==========Tree view of Employee Indent Advance==========-->
    <record id="employeeIndent_request_tree_view" model="ir.ui.view">
        <field name="name">indent.request.tree</field>
        <field name="model">indent.request</field>
        <field name="arch" type="xml">
            <tree string="Indent">
                <field name="indent_sequence"/>
                <field name="employee_id"/>
                <field name="branch_id" readonly="1"/>
                <field name="job_id" readonly="1"/>
                <field name="department_id" readonly="1"/>
                <field name="state"/>
            </tree>
        </field>
    </record>
    

    <!--==========Search view of Employee Indent Advance Status==========-->
     <record id="view_Indent_request_status_filter_report" model="ir.ui.view">
        <field name="name">indent.request.search</field>
        <field name="model">indent.request</field>
        <field name="arch" type="xml">
            <search string="Search for Indent Request">
                <field name="indent_sequence"/>
                <group expand="0" string="Group By">
                   <filter name="group_category" string="State" context="{'group_by':'state'}"/>
                </group>
            </search>
        </field>
    </record>

     <!--=====Sequence of Employee Indent Advance=====-->
     <record id="seq_indent_sequence" model="ir.sequence">
        <field name="name">Indent sequence</field>
        <field name="code">indent.request</field>
        <field name="padding">3</field>
        <field name="company_id" eval="False"/>
     </record>

    <!--===============Action view of Employee Indent Advance===============-->
    <record id="hremployeeIndent_request_action" model="ir.actions.act_window">
        <field name="name">Indent Request</field>
        <field name="res_model">indent.request</field>
        <field name="view_type">form</field>
        <field name="view_mode">tree,form,search</field>
        <field name="context">{'default_indent_type': 'issue'}</field>
    </record>

    <!--============Action view of Employee Indent Advance Draft============-->
    <record id="employeeIndent_request_action_draft" model="ir.actions.act_window">
        <field name="name">Indent Request</field>
        <field name="res_model">indent.request</field>
        <field name="view_type">form</field>
        <field name="view_mode">tree,form</field>
        <field name="search_view_id" ref="view_Indent_request_status_filter_report"/>
        <field name="context">{'default_indent_type': 'issue'}</field>
        <field name="domain">[('state','=','draft'),('indent_type','=','issue')]</field>
    </record>

    <!--============Action view of Employee Indent Advance To Approve============-->
    <record id="employeeIndent_request_action_to_approve" model="ir.actions.act_window">
        <field name="name">Indent Request</field>
        <field name="res_model">indent.request</field>
        <field name="view_type">form</field>
        <field name="view_mode">tree,form</field>
        <field name="context">{'default_indent_type': 'issue'}</field>
        <field name="search_view_id" ref="view_Indent_request_status_filter_report"/>
        <field name="domain">[('state','=','to_approve'),('indent_type','=','issue')]</field>
    </record>


    <!--============Action view of Employee Indent Advance Approved============-->
    <record id="employeeIndent_request_action_approved" model="ir.actions.act_window">
        <field name="name">Indent Request</field>
        <field name="res_model">indent.request</field>
        <field name="view_type">form</field>
        <field name="view_mode">tree,form</field>
        <field name="context">{'default_indent_type': 'issue'}</field>
        <field name="search_view_id" ref="view_Indent_request_status_filter_report"/>
        <field name="domain">[('state','=','approved'),('indent_type','=','issue')]</field>
    </record>


    <!--============Action view of Employee Indent Advance Rejected============-->
    <record id="employeeIndent_request_action_rejected" model="ir.actions.act_window">
        <field name="name">Indent Request</field>
        <field name="res_model">indent.request</field>
        <field name="view_type">form</field>
        <field name="view_mode">tree,form</field>
        <field name="context">{'default_indent_type': 'issue'}</field>
        <field name="search_view_id" ref="view_Indent_request_status_filter_report"/>
        <field name="domain">[('state','=','rejected'),('indent_type','=','issue')]</field>
    </record>




<!--===============Action view of Employee Indent Advance Status=================-->
    <record id="menu_Indent_reporting_request_status_action" model="ir.actions.act_window">
        <field name="name">Indent/GRN  - Status</field>
        <field name="res_model">indent.request</field>
        <!--<field name="view_type">form</field>-->
        <field name="view_mode">tree,form,search</field>
        <field name="context">{'group_by': 'state'}</field>
    </record>


<!--===============Action view of Employee Indent Advance Department=================-->
    <record id="menu_Indent_reporting_request_department_action" model="ir.actions.act_window">
        <field name="name">Indent/GRN Request</field>
        <field name="res_model">indent.request</field>
        <!--<field name="view_type">form</field>-->
        <field name="view_mode">tree,form,search</field>
        <field name="context">{'group_by': 'department_id'}</field>
    </record>


<!--===============Action view of Employee Indent Advance Job=================-->
    <record id="menu_Indent_reporting_request_job_action" model="ir.actions.act_window">
        <field name="name">Indent/GRN - Functional Designation</field>
        <field name="res_model">indent.request</field>
        <!--<field name="view_type">form</field>-->
        <field name="view_mode">tree,form,search</field>
        <field name="context">{'group_by': 'job_id'}</field>
    </record>


<!--===============Action view of Employee Indent Advance Branch=================-->
    <record id="menu_Indent_reporting_request_branch_action" model="ir.actions.act_window">
        <field name="name">Indent/GRN - Branch</field>
        <field name="res_model">indent.request</field>
        <!--<field name="view_type">form</field>-->
        <field name="view_mode">tree,form,search</field>
        <field name="context">{'group_by': 'branch_id'}</field>
    </record>

<!--===============Action view of Employee Indent Advance Branch=================-->
    <record id="menu_Indent_reporting_request_type_action" model="ir.actions.act_window">
        <field name="name">Indent/GRN - Type</field>
        <field name="res_model">indent.request</field>
        <!--<field name="view_type">form</field>-->
        <field name="view_mode">tree,form,search</field>
        <field name="context">{'group_by': 'indent_type'}</field>
    </record>



    <!--=Menu Item of Indent menu snd their submenu=-->
    <menuitem name="Indent"
              id="menu_Indent"
              web_icon="indent_stpi,static/description/icon.png"
              sequence="21"/>
    
    <menuitem name="Indent Request"
                id="menu_Indent_request" parent="menu_Indent"
              sequence="1"
                />

    <menuitem name="New"
                id="menu_Indent_request_apply_draft" parent="menu_Indent_request"
                 action="employeeIndent_request_action_draft"
                 />
    <menuitem name="To Approve"
                id="menu_Indent_request_apply_to_approve" parent="menu_Indent_request"
                 action="employeeIndent_request_action_to_approve"
                 />
    <menuitem name="Approved"
                id="menu_Indent_request_apply_approved" parent="menu_Indent_request"
                 action="employeeIndent_request_action_approved"
                 />
    <menuitem name="Rejected"
                id="menu_Indent_request_apply_rejected" parent="menu_Indent_request"
                 action="employeeIndent_request_action_rejected"
                 />


    <menuitem name="Reporting"
            id="menu_Indent_reporting" parent="menu_Indent"
              sequence="5"
            />

    <menuitem name="Indent Request"
            id="menu_Indent_reporting_request" parent="menu_Indent_reporting"
            />
        <menuitem name="All"
                id="menu_Indent_request_apply" parent="menu_Indent_reporting_request"
                 action="hremployeeIndent_request_action"
                 />
    <menuitem name="Indent by status"
                id="menu_Indent_reporting_request_status" parent="menu_Indent_reporting_request"
                 action="menu_Indent_reporting_request_status_action"
                 />
    <menuitem name="Indent by Department"
                id="menu_Indent_reporting_request_department" parent="menu_Indent_reporting_request"
                 action="menu_Indent_reporting_request_department_action"
                 />
    <menuitem name="Indent by Functional Designation"
                id="menu_Indent_reporting_request_job" parent="menu_Indent_reporting_request"
                 action="menu_Indent_reporting_request_job_action"
                 />
    <menuitem name="Indent by Type"
                id="menu_Indent_reporting_request_job" parent="menu_Indent_reporting_request"
                 action="menu_Indent_reporting_request_job_action"
                 />
    <menuitem name="Indent by Branch"
                id="menu_Indent_reporting_request_type" parent="menu_Indent_reporting_request"
                 action="menu_Indent_reporting_request_type_action"
                 />




     <!--=====Sequence of Employee Indent Advance=====-->
     <record id="seq_grn_sequence" model="ir.sequence">
        <field name="name">GRN sequence</field>
        <field name="code">grn.seqid</field>
        <field name="padding">3</field>
        <field name="company_id" eval="False"/>
     </record>


    <!--============Action view of Employee Indent Advance Draft============-->
    <record id="grn_Indent_request_action_draft" model="ir.actions.act_window">
        <field name="name">GRN</field>
        <field name="res_model">indent.request</field>
        <field name="view_type">form</field>
        <field name="view_mode">tree,form</field>
<!--        <field name="context">{'search_default_my_tour': 1}</field>-->
        <field name="search_view_id" ref="view_Indent_request_status_filter_report"/>
        <field name="context">{'default_indent_type': 'grn'}</field>
        <field name="domain">[('state','=','draft'),('indent_type','=','grn')]</field>
    </record>

    <!--============Action view of Employee Indent Advance To Approve============-->
    <record id="grn_Indent_request_action_to_approve" model="ir.actions.act_window">
        <field name="name">GRN</field>
        <field name="res_model">indent.request</field>
        <field name="view_type">form</field>
        <field name="view_mode">tree,form</field>
        <field name="context">{'default_indent_type': 'grn'}</field>
        <field name="search_view_id" ref="view_Indent_request_status_filter_report"/>
        <field name="domain">[('state','=','to_approve'),('indent_type','=','grn')]</field>
    </record>


    <!--============Action view of Employee Indent Advance Approved============-->
    <record id="grn_Indent_request_action_approved" model="ir.actions.act_window">
        <field name="name">GRN</field>
        <field name="res_model">indent.request</field>
        <field name="view_type">form</field>
        <field name="view_mode">tree,form</field>
        <field name="context">{'default_indent_type': 'grn'}</field>
        <field name="search_view_id" ref="view_Indent_request_status_filter_report"/>
        <field name="domain">[('state','=','approved'),('indent_type','=','grn')]</field>
    </record>


    <!--============Action view of Employee Indent Advance Rejected============-->
    <record id="grn_Indent_request_action_rejected" model="ir.actions.act_window">
        <field name="name">GRN</field>
        <field name="res_model">indent.request</field>
        <field name="view_type">form</field>
        <field name="view_mode">tree,form</field>
        <field name="context">{'default_indent_type': 'grn'}</field>
        <field name="search_view_id" ref="view_Indent_request_status_filter_report"/>
        <field name="domain">[('state','=','rejected')]</field>
    </record>



    <menuitem name="GRN"
                id="menu_grn_Indent_request" parent="menu_Indent"
              sequence="2"
                 />


    <menuitem name="New"
                id="menu_grn_Indent_request_apply_draft" parent="menu_grn_Indent_request"
                 action="grn_Indent_request_action_draft"
                 />
    <menuitem name="To Approve"
                id="menu_grn_Indent_request_apply_to_approve" parent="menu_grn_Indent_request"
                 action="grn_Indent_request_action_to_approve"
                 />
    <menuitem name="Approved"
                id="menu_grn_Indent_request_apply_approved" parent="menu_grn_Indent_request"
                 action="grn_Indent_request_action_approved"
                 />
    <menuitem name="Rejected"
                id="menu_grn_Indent_request_apply_rejected" parent="menu_grn_Indent_request"
                 action="grn_Indent_request_action_rejected"
                 />



</odoo>

